SPARQLWrapper/KeyCaseInsensitiveDict.py
SPARQLWrapper/SPARQLExceptions.py
SPARQLWrapper/SmartWrapper.py
SPARQLWrapper/Wrapper.py
SPARQLWrapper/__init__.py
SPARQLWrapper/main.py
SPARQLWrapper/py.typed
SPARQLWrapper/sparql_dataframe.py
SPARQLWrapper-2.0.0.dist-info/AUTHORS.md
SPARQLWrapper-2.0.0.dist-info/LICENSE.txt
SPARQLWrapper-2.0.0.dist-info/METADATA
SPARQLWrapper-2.0.0.dist-info/WHEEL
SPARQLWrapper-2.0.0.dist-info/entry_points.txt
SPARQLWrapper-2.0.0.dist-info/top_level.txt
SPARQLWrapper-2.0.0.dist-info/RECORD
