Metadata-Version: 2.1
Name: SPARQLWrapper
Version: 2.0.0
Summary: SPARQL Endpoint interface to Python
Home-page: http://rdflib.github.io/sparqlwrapper
Download-URL: https://github.com/RDFLib/sparqlwrapper/releases
Author: Ivan Herman, Sergio Fernández, Carlos Tejo Alonso, Alexey Zakhlestin
Author-email: rdflib-dev@googlegroups.com
License: W3C SOFTWARE NOTICE AND LICENSE
Project-URL: Home, https://rdflib.github.io/sparqlwrapper
Project-URL: Documentation, https://sparqlwrapper.readthedocs.io
Project-URL: Source, https://github.com/RDFLib/sparqlwrapper
Project-URL: Tracker, https://github.com/RDFLib/sparqlwrapper/issues
Keywords: python,sparql,rdf,rdflib
Platform: any
Classifier: Development Status :: 5 - Production/Stable
Classifier: Intended Audience :: Developers
Classifier: License :: OSI Approved :: W3C License
Classifier: Operating System :: OS Independent
Classifier: Programming Language :: Python :: 3
Classifier: Programming Language :: Python :: 3.7
Classifier: Programming Language :: Python :: 3.8
Classifier: Programming Language :: Python :: 3.9
Classifier: Programming Language :: Python :: 3.10
Classifier: Programming Language :: Python :: Implementation :: CPython
Classifier: Topic :: Software Development :: Libraries :: Python Modules
Requires-Python: >=3.7
Provides-Extra: dev
Provides-Extra: pandas
Provides-Extra: keepalive
Provides-Extra: docs
License-File: LICENSE.txt
License-File: AUTHORS.md
